{
  "name": "<%= _.slugify(appname) %>",
  "version": "0.0.1",
  "dependencies": {<% if (cssFramework === 'SASSBootstrap') { %>
    "sass-bootstrap": "*",<% } %><% if (includeFontAwesome) { %>
    "font-awesome": "*",<% } %><% if (includeLodash) { %>
    "lodash": "*",<% } %><% if (includeModernizr) { %>
    "modernizr": "*",<% } %>
    "jquery": "*",<% if (includeButtonCss) { %>
    "Buttons": "*",<% } %><% if (includeAnimateCss) { %>
    "animate-sass": "*",<% } %>
    "requirejs": "*",
    "modernizr": "*"  
  }
}

